mcafee_epo_policies/__init__.py
mcafee_epo_policies/constants.py
mcafee_epo_policies/policies.py
mcafee_epo_policies/es/__init__.py
mcafee_epo_policies/es/fw/__init__.py
mcafee_epo_policies/es/fw/esfwpolicies.py
mcafee_epo_policies/es/fw/rules.py
mcafee_epo_policies/es/tp/__init__.py
mcafee_epo_policies/es/tp/estppolicies.py
mcafee_epo_policies/es/tp/exclusions.py
mcafee_epo_policies/es/tp/onaccessscan.py
mcafee_epo_policies/es/tp/ondemandscan.py
mcafee_epo_policies/ma/__init__.py
mcafee_epo_policies/ma/__root__.ca
mcafee_epo_policies/ma/__signer__.ca
mcafee_epo_policies/ma/general.py
mcafee_epo_policies/ma/mapolicies.py
mcafee_epo_policies/ma/repository.py
mcafee_epo_policies-0.0.6.dist-info/LICENSE
mcafee_epo_policies-0.0.6.dist-info/METADATA
mcafee_epo_policies-0.0.6.dist-info/WHEEL
mcafee_epo_policies-0.0.6.dist-info/top_level.txt
mcafee_epo_policies-0.0.6.dist-info/RECORD
