Metadata-Version: 2.1
Name: mcafee-epo-policies
Version: 0.0.6
Summary: McAfee ePolicy Orchestrator Polices Python Class Library
Home-page: https://github.com/bmarandel/mcafee-epo-policies
Author: Benjamin Marandel
License: Apache License 2.0
Platform: any
Classifier: Development Status :: 3 - Alpha
Classifier: Intended Audience :: System Administrators
Classifier: Operating System :: OS Independent
Classifier: License :: OSI Approved :: Apache Software License
Classifier: Topic :: Software Development :: Libraries :: Python Modules
Classifier: Programming Language :: Python :: 3.6
Classifier: Programming Language :: Python :: 3.7
Classifier: Programming Language :: Python :: 3.8
